{
    "0" : {
        "situation" : "A makes the varsity team while B does not",
        "negation_switch" : {"0" : ["is", "isn't"], 
                             "1" : ["has", "does not have"], 
                             "2" : ["makes", "does not make"]},
        "antonym_switch" : ["skilled", "incompetent"],
        "original_comparison" : "is more skilled than",
        "paraphrase" : "has more skill than",
        "inverted_paraphrase" : "makes less mistakes than",
        "premise_switch" : {"0" : ["more", "less"], 
                            "1" : ["more", "less"], 
                            "2" : ["less", "more"]},
        "template" : "4"
    },

    "1" : {
        "situation" : "A is going to perform for people while B is not",
        "negation_switch" : {"0" : ["is", "isn't"], 
                             "1" : ["is", "isn't"], 
                             "2" : ["is", "isn't"]},
        "antonym_switch" : ["nervous", "relaxed"],
        "original_comparison" : "is more nervous than",
        "paraphrase" : "is more stressed than",
        "inverted_paraphrase" : "is feeling less calm than",
        "premise_switch" : {"0" : ["more", "less"], 
                            "1" : ["more", "less"], 
                            "2" : ["less", "more"]},
        "template" : "4"
    },

    "2" : {
        "situation" : "A won the competition while B did not",
        "negation_switch" : {"0" : ["is", "isn't"], 
                             "1" : ["is", "isn't"], 
                             "2" : ["is", "isn't"]},
        "antonym_switch" : ["happy", "sad"],
        "original_comparison" : "is more happy than",
        "paraphrase" : "is feeling more happiness than",
        "inverted_paraphrase" : "is frowning less than",
        "premise_switch" : {"0" : ["more", "less"], 
                            "1" : ["more", "less"], 
                            "2" : ["less", "more"]},
        "template" : "4"
    },

    "3" : {
        "situation" : "A is able to concentrate more than B",
        "negation_switch" : {"0" : ["is", "isn't"], 
                             "1" : ["is", "isn't"], 
                             "2" : ["wastes", "does not waste"]},
        "antonym_switch" : ["effective", "unproductive"],
        "original_comparison" : "is more effective than",
        "paraphrase" : "is able to do more work than",
        "inverted_paraphrase" : "wastes less time than",
        "premise_switch" : {"0" : ["more", "less"], 
                            "1" : ["more", "less"], 
                            "2" : ["less", "more"]},
        "template" : "5"
    },

    "4" : {
        "situation" : "A bullies people while B does not",
        "negation_switch" : {"0" : ["is", "isn't"], 
                             "1" : ["is", "isn't"], 
                             "2" : ["cares", "does not care"]},
        "antonym_switch" : ["mean", "kind"],
        "original_comparison" : "is more mean than",
        "paraphrase" : "is a more cruel person than",
        "inverted_paraphrase" : "cares less about people than",
        "premise_switch" : {"0" : ["more", "less"], 
                            "1" : ["more", "less"], 
                            "2" : ["less", "more"]},
        "template" : "4"
    },

    "5" : {
        "situation" : "A is B's boss",
        "negation_switch" : {"0" : ["commands", "does not command"], 
                             "1" : ["has", "has not"], 
                             "2" : ["should", "should not"]},
        "antonym_switch" : ["respect", "dishonor"],
        "original_comparison" : "commands more respect than",
        "paraphrase" : "has earned more respect than",
        "inverted_paraphrase" : "should be disrespected less than",
        "premise_switch" : {"0" : ["more", "less"], 
                            "1" : ["more", "less"], 
                            "2" : ["less", "more"]},
        "template" : "3"
    },

    "6" : {
        "situation" : "A has more work than B",
        "negation_switch" : {"0" : ["is", "is not"], 
                             "1" : ["has", "does not have"], 
                             "2" : ["should", "should not"]},
        "antonym_switch" : ["stressed out", "at ease"],
        "original_comparison" : "is more stressed out than",
        "paraphrase" : "has higher stress levels than",
        "inverted_paraphrase" : "should be less calm than",
        "premise_switch" : {"0" : ["more", "less"], 
                            "1" : ["higher", "lower"], 
                            "2" : ["less", "more"]},
        "template" : "5"
    },

    "7" : {
        "situation" : "A has a crush on B",
        "negation_switch" : {"0" : ["is", "is not"], 
                             "1" : ["feels", "does not feel"], 
                             "2" : ["is", "is not"]},
        "antonym_switch" : ["awkward", "relaxed"],
        "original_comparison" : "is more awkward around",
        "paraphrase" : "feels more awkward around",
        "inverted_paraphrase" : "is less at ease around",
        "premise_switch" : {"0" : ["more", "less"], 
                            "1" : ["more", "less"], 
                            "2" : ["less", "more"]},
        "template" : "3"
    },

    "8" : {
        "situation" : "A has more dedication than B",
        "negation_switch" : {"0" : ["is", "is not"], 
                             "1" : ["has", "does not have"], 
                             "2" : ["has", "does not have"]},
        "antonym_switch" : ["succeed", "fail"],
        "original_comparison" : "is more likely to succeed than",
        "paraphrase" : "has more chance to succeed than",
        "inverted_paraphrase" : "has less chance of failing than",
        "premise_switch" : {"0" : ["more", "less"], 
                            "1" : ["more", "less"], 
                            "2" : ["less", "more"]},
        "template" : "5"
    },

    "9" : {
        "situation" : "A is B's parent",
        "negation_switch" : {"0" : ["takes", "does not take"], 
                             "1" : ["provides", "does not provide"], 
                             "2" : ["relies", "does not rely"]},
        "antonym_switch" : ["care of", "assistance from"],
        "original_comparison" : "initially takes more care of",
        "paraphrase" : "initially provides more for",
        "inverted_paraphrase" : "initially relies less on",
        "premise_switch" : {"0" : ["more", "less"], 
                            "1" : ["more", "less"], 
                            "2" : ["less", "more"]},
        "template" : "3"
    },

    "10" : {
        "situation" : "A is B's doctor",
        "negation_switch" : {"0" : ["takes", "does not take"], 
                             "1" : ["provides", "does not provide"], 
                             "2" : ["requires", "does not require"]},
        "antonym_switch" : ["care of", "assistance from"],
        "original_comparison" : "takes more care of",
        "paraphrase" : "provides more assistance towards",
        "inverted_paraphrase" : "requires less medical aid from",
        "premise_switch" : {"0" : ["more", "less"], 
                            "1" : ["more", "less"], 
                            "2" : ["less", "more"]},
        "template" : "3"
    },

    "11" : {
        "situation" : "A hurt B's feelings",
        "negation_switch" : {"0" : ["must", "must not"], 
                             "1" : ["should", "should not"], 
                             "2" : ["should", "should not"]},
        "antonym_switch" : ["thoughtful", "insensitive"],
        "original_comparison" : "must be more thoughtful than",
        "paraphrase" : "should be more caring than",
        "inverted_paraphrase" : "should be less selfish towards",
        "premise_switch" : {"0" : ["more", "less"], 
                            "1" : ["more", "less"], 
                            "2" : ["less", "more"]},
        "template" : "3"
    },

    "12" : {
        "situation" : "A is B's priest",
        "negation_switch" : {"0" : ["spends", "does not spend"], 
                             "1" : ["can", "can not"], 
                             "2" : ["is", "is not"]},
        "antonym_switch" : ["praying", "sinning"],
        "original_comparison" : "spends more time praying than",
        "paraphrase" : "can be found praying more often than",
        "inverted_paraphrase" : "is less likely to sin than",
        "premise_switch" : {"0" : ["more", "less"], 
                            "1" : ["more", "less"], 
                            "2" : ["less", "more"]},
        "template" : "3"
    },

    "13" : {
        "situation" : "A is B's lawyer",
        "negation_switch" : {"0" : ["is", "is not"], 
                             "1" : ["has", "has not"], 
                             "2" : ["is", "is not"]},
        "antonym_switch" : ["knowledgeable about", "ignorant of"],
        "original_comparison" : "is more knowledgeable about law than",
        "paraphrase" : "has studied law more than",
        "inverted_paraphrase" : "is less clueless about the law than",
        "premise_switch" : {"0" : ["more", "less"], 
                            "1" : ["more", "less"], 
                            "2" : ["less", "more"]},
        "template" : "3"
    },

    "14" : {
        "situation" : "A has a lot more money than B",
        "negation_switch" : {"0" : ["is", "is not"], 
                             "1" : ["is", "is not"], 
                             "2" : ["worries", "does not worry"]},
        "antonym_switch" : ["secure", "unstable"],
        "original_comparison" : "is more financially secure than",
        "paraphrase" : "is more able to pay bills than",
        "inverted_paraphrase" : "worries less about bankruptcy",
        "premise_switch" : {"0" : ["more", "less"], 
                            "1" : ["more", "less"], 
                            "2" : ["less", "more"]},
        "template" : "5"
    },

    "15" : {
        "situation" : "A watches more tv shows than B",
        "negation_switch" : {"0" : ["is", "is not"], 
                             "1" : ["has", "does not have"], 
                             "2" : ["is", "is not"]},
        "antonym_switch" : ["capable of understanding", "unable to understand"],
        "original_comparison" : "is more capable of understanding pop-culture referneces than",
        "paraphrase" : "has more knowledge about current pop-culture than",
        "inverted_paraphrase" : "is less ignorant about pop-culture than",
        "premise_switch" : {"0" : ["more", "less"], 
                            "1" : ["more", "less"], 
                            "2" : ["less", "more"]},
        "template" : "5"
    },

    "16" : {
        "situation" : "A always beats B in tennis",
        "negation_switch" : {"0" : ["is", "is not"], 
                             "1" : ["has", "has not"], 
                             "2" : ["is", "is not"]},
        "antonym_switch" : ["proficient", "inadequate"],
        "original_comparison" : "is a more proficient tennis player than",
        "paraphrase" : "has more skill in tennis than",
        "inverted_paraphrase" : "is less incompetent in tennis than",
        "premise_switch" : {"0" : ["more", "less"], 
                            "1" : ["more", "less"], 
                            "2" : ["less", "more"]},
        "template" : "3"
    },

    "17" : {
        "situation" : "A makes B late",
        "negation_switch" : {"0" : ["has", "has not"], 
                             "1" : ["should", "should not be"], 
                             "2" : ["has", "has not"]},
        "antonym_switch" : ["annoyed at", "contrite towards"],
        "original_comparison" : "has less reason to be annoyed at",
        "paraphrase" : "should be less upset with",
        "inverted_paraphrase" : "has more reason to be apologetic towards",
        "premise_switch" : {"0" : ["less", "more"], 
                            "1" : ["less", "more"], 
                            "2" : ["more", "less"]},
        "template" : "3"
    },

    "18" : {
        "situation" : "A is a better friend than B",
        "negation_switch" : {"0" : ["is", "is not"], 
                             "1" : ["shows", "does not show"], 
                             "2" : ["is", "is not"]},
        "antonym_switch" : ["thoughtful", "selfish"],
        "original_comparison" : "is more thoughtful than",
        "paraphrase" : "shows more care towards friends than",
        "inverted_paraphrase" : "is less of a prick than",
        "premise_switch" : {"0" : ["more", "less"], 
                            "1" : ["more", "less"], 
                            "2" : ["less", "more"]},
        "template" : "5"
    },

    "19" : {
        "situation" : "A is B's teacher",
        "negation_switch" : {"0" : ["should", "should not"], 
                             "1" : ["should", "should not"], 
                             "2" : ["is", "is not"]},
        "antonym_switch" : ["informed", "ignorant"],
        "original_comparison" : "should be more informed than",
        "paraphrase" : "should have more understanding of the material than",
        "inverted_paraphrase" : "is less unaware of the subject than",
        "premise_switch" : {"0" : ["more", "less"], 
                            "1" : ["more", "less"], 
                            "2" : ["less", "more"]},
        "template" : "3"
    }
}